panfeed/__init__.py
panfeed/__main__.py
panfeed/classes.py
panfeed/colorlog.py
panfeed/get_clusters.py
panfeed/get_kmers.py
panfeed/input.py
panfeed/panfeed.py
panfeed/plot.py
panfeed-1.7.2.dist-info/METADATA
panfeed-1.7.2.dist-info/WHEEL
panfeed-1.7.2.dist-info/entry_points.txt
panfeed-1.7.2.dist-info/licenses/LICENSE
panfeed-1.7.2.dist-info/RECORD
