Metadata-Version: 2.4
Name: panfeed
Version: 1.7.2
Summary: Compute gene-cluster specific k-mers over a pangenome
Project-URL: Homepage, https://github.com/microbial-pangenomes-lab/panfeed
Project-URL: Bug Tracker, https://github.com/microbial-pangenomes-lab/panfeed/issues
Author-email: Hannes Neubauer <neubauer.hannes@mh-hannover.de>, Marco Galardini <galardini.marco@mh-hannover.de>
License:                                  Apache License
License-File: LICENSE
Classifier: Development Status :: 4 - Beta
Classifier: Intended Audience :: Science/Research
Classifier: License :: OSI Approved :: Apache Software License
Classifier: Programming Language :: Python :: 3
Classifier: Topic :: Scientific/Engineering :: Bio-Informatics
Requires-Python: >=3.6
Requires-Dist: matplotlib
Requires-Dist: numpy
Requires-Dist: pandas
Requires-Dist: pyfaidx
Requires-Dist: seaborn
